Workbook

Sheet Premissas
A1: IBITI Glamping G04 - Premissas do Valuation
A2: Documento de trabalho - set/2026 | Valuation com convenção mid-period validada em aula
A4: 1. Premissas operacionais
A5: Parametro | B5: Valor | C5: Nota
A6: Diaria media ano 1 (R$) | B6: 7333 | C6: Parceiro
A7: Consumo medio / hospedagem ano 1 (R$) | B7: 2000 | C7: Parceiro
A8: Estadia media (noites) | B8: 3 | C8: Converte diarias em hospedagens
A9: Dias / mes | B9: 30 | C9: 360 dias/ano
A10: Ticket medio ano 1 (R$) | B10: =B6*B8+B7 -> 23999 | C10: diaria x estadia + consumo
A11: Reajuste ticket a.a. | B11: 0.1 | C11: Sobe diaria E consumo (composto)
A12: Royalty IBITI | B12: 0.15 | C12: Sobre faturamento bruto
A13: Tendas 2027 | B13: 6 | C13: Ano 1
A14: Tendas 2028-2030 | B14: 20 | C14: Expansao a partir de 2028
A15: N tokens I | B15: 100 | C15: Supply fixo
A16: Tokens vendidos (externos) | B16: =ROUND(B15*2/3,0) -> 67 | C16: ~ 2/3 do supply
A17: Tokens tesouraria IBITI | B17: =B15-B16 -> 33 | C17: ~ 1/3 do supply
A18: Fat100 - 6 tendas (precos ano 1) | B18: =B9*B13*12*B6+(B9*B13*12/B8)*B7 -> 17279280 | C18: Capacidade a 100%
A19: Fat100 - 20 tendas (precos ano 1) | B19: =B9*B14*12*B6+(B9*B14*12/B8)*B7 -> 57597600 | C19: Capacidade a 100%
A21: 2. Premissas Token B (beneficios)
A22: Parametro | B22: Valor/unidades | C22: Nota
A23: Tokens B por Token I por ano | B23: 8 | C23: Credito anual
A24: Valor de face Token B (R$) | B24: 780 | C24: Mediana do catalogo a preco de resgate
A25: Custeio anual (R$) | B25: =B23*B24 -> 6240 | C25: 8 x 780
A26: Custeio total 4 anos (R$) | B26: =B25*4 -> 24960 | C26: Abate do payout (caixa)
A27: Equivalente a preco de tabela / ano (R$) | B27: =B25/(1-B29) -> 10400 | C27: Custeio / 0,60
A28: Equivalente a preco de tabela / 4 anos (R$) | B28: =B26/(1-B29) -> 41600 | C28: 24960 / 0,60 = 41600
A29: Desconto do catalogo | B29: 0.4 | C29: Holder paga 60% da tabela
A30: Premissa de uso | B30: 1 | C30: Holders utilizam os beneficios
A31: 3. Cenarios de ocupacao
A32: Cenario | B32: 2027 | C32: 2028 | D32: 2029 | E32: 2030 | F32: Logica
A33: Pessimista | B33: 0.38 | C33: 0.38 | D33: 0.38 | E33: 0.38 | F33: 38% fixo
A34: Base | B34: 0.38 | C34: 0.4 | D34: 0.45 | E34: 0.5 | F34: Base G04
A35: Otimista | B35: 0.38 | C35: 0.5 | D35: 0.5 | E35: 0.5 | F35: 38% depois 50%
A36: Expansao (queda ano 2) | B36: 0.38 | C36: 0.28 | D36: 0.4 | E36: 0.48 | F36: Diluicao na expansao 6 para 20; depois recupera
A37: Nota: o cenario Expansao modela queda de ocupacao no 2o ano porque a capacidade triplica (6 para 20) e a demanda nao acompanha na mesma velocidade. Curva: 38/28/40/48. Ajustavel pelo grupo.

Sheet Valuation
A1: IBITI - Valuation do Token I (4 cenarios)
A2: Preço = VP dos payouts brutos descontados a Ke pela convenção MID-PERIOD validada pelo professor (t = 0,5; 1,5; 2,5; 3,5). Captação = 67 tokens externos x preço.
A3: Convenção temporal única: 2027=t0,5; 2028=t1,5; 2029=t2,5; 2030=t3,5. O primeiro fluxo também é descontado, mas pelo ponto médio do período.
A4: RESUMO COMPARATIVO - MID-PERIOD
A5: Cenario | B5: VF Faturamento | C5: VF Royalty 15% | D5: VF Payout / token | E5: VP integral (100) | F5: Preco token (VP) | G5: Captacao IBITI (67 tokens) | H5: Caixa liquido VF | I5: Rend. medio a.a. (c/ benef. face) | J5: Rend. medio a.a. (c/ benef. tabela) | K5: TIR econ. (face) | L5: TIR caixa | M5: TIR econ. (tabela)
A6: Pessimista | B6: =I22 -> 86257014 | C6: =J22 -> 12938552 | D6: =K22 -> 129385.52 | E6: =B24 -> 9081858.8 | F6: =E6/Premissas!$B$15 -> 90818.588 | G6: =F6*Premissas!$B$16 -> 6084845.4 | H6: =M22 -> 104425.52 | I6: =U22 -> 0.35616476 | J6: =V22 -> 0.40197036 | K6: =Ke_WACC!$B$14 -> 0.163574 | L6: =XIRR(AB6:AF6,$AL$6:$AP$6) -> 0.057845742 | M6: =IRR(AG6:AK6) -> 0.18658553 | W6: =-F6 -> -90818.588 | X6: =K18 -> 9849.1896 | Y6: =K19 -> 36113.695 | Z6: =K20 -> 39725.065 | AA6: =K21 -> 43697.571 | AB6: =-F6 -> -90818.588 | AC6: =M18 -> 3609.1896 | AD6: =M19 -> 29873.695 | AE6: =M20 -> 33485.065 | AF6: =M21 -> 37457.571 | AG6: =-F6 -> -90818.588 | AH6: =M18+O18 -> 14009.19 | AI6: =M19+O19 -> 40273.695 | AJ6: =M20+O20 -> 43885.065 | AK6: =M21+O21 -> 47857.571 | AL6: 46388 | AM6: 46570 | AN6: 46936 | AO6: 47301 | AP6: 47666
A7: Base | B7: =I35 -> 1.0160217e+08 | C7: =J35 -> 15240325 | D7: =K35 -> 152403.25 | E7: =B37 -> 10546396 | F7: =E7/Premissas!$B$15 -> 105463.96 | G7: =F7*Premissas!$B$16 -> 7066085.5 | H7: =M35 -> 127443.25 | I7: =U35 -> 0.36126854 | J7: =V35 -> 0.4007133 | K7: =Ke_WACC!$B$14 -> 0.163574 | L7: =XIRR(AB7:AF7,$AL$7:$AP$7) -> 0.076456736 | M7: =IRR(AG7:AK7) -> 0.17864576 | W7: =-F7 -> -105463.96 | X7: =K31 -> 9849.1896 | Y7: =K32 -> 38014.416 | Z7: =K33 -> 47042.84 | AA7: =K34 -> 57496.804 | AB7: =-F7 -> -105463.96 | AC7: =M31 -> 3609.1896 | AD7: =M32 -> 31774.416 | AE7: =M33 -> 40802.84 | AF7: =M34 -> 51256.804 | AG7: =-F7 -> -105463.96 | AH7: =M31+O31 -> 14009.19 | AI7: =M32+O32 -> 42174.416 | AJ7: =M33+O33 -> 51202.84 | AK7: =M34+O34 -> 61656.804 | AL7: 46388 | AM7: 46570 | AN7: 46936 | AO7: 47301 | AP7: 47666
A8: Otimista | B8: =I48 -> 1.1142256e+08 | C8: =J48 -> 16713384 | D8: =K48 -> 167133.84 | E8: =B50 -> 11661477 | F8: =E8/Premissas!$B$15 -> 116614.77 | G8: =F8*Premissas!$B$16 -> 7813189.4 | H8: =M48 -> 142173.84 | I8: =U48 -> 0.35830333 | J8: =V48 -> 0.39397634 | K8: =Ke_WACC!$B$14 -> 0.163574 | L8: =XIRR(AB8:AF8,$AL$8:$AP$8) -> 0.082819867 | M8: =IRR(AG8:AK8) -> 0.17452658 | W8: =-F8 -> -116614.77 | X8: =K44 -> 9849.1896 | Y8: =K45 -> 47518.02 | Z8: =K46 -> 52269.822 | AA8: =K47 -> 57496.804 | AB8: =-F8 -> -116614.77 | AC8: =M44 -> 3609.1896 | AD8: =M45 -> 41278.02 | AE8: =M46 -> 46029.822 | AF8: =M47 -> 51256.804 | AG8: =-F8 -> -116614.77 | AH8: =M44+O44 -> 14009.19 | AI8: =M45+O45 -> 51678.02 | AJ8: =M46+O46 -> 56429.822 | AK8: =M47+O47 -> 61656.804 | AL8: 46388 | AM8: 46570 | AN8: 46936 | AO8: 47301 | AP8: 47666
A9: Expansao (queda ano 2) | B9: =I61 -> 88981380 | C9: =J61 -> 13347207 | D9: =K61 -> 133472.07 | E9: =B63 -> 9144541 | F9: =E9/Premissas!$B$15 -> 91445.41 | G9: =F9*Premissas!$B$16 -> 6126842.5 | H9: =M61 -> 108512.07 | I9: =U61 -> 0.36489549 | J9: =V61 -> 0.41038711 | K9: =Ke_WACC!$B$14 -> 0.163574 | L9: =XIRR(AB9:AF9,$AL$9:$AP$9) -> 0.066074659 | M9: =IRR(AG9:AK9) -> 0.1850961 | W9: =-F9 -> -91445.41 | X9: =K57 -> 9849.1896 | Y9: =K58 -> 26610.091 | Z9: =K59 -> 41815.858 | AA9: =K60 -> 55196.932 | AB9: =-F9 -> -91445.41 | AC9: =M57 -> 3609.1896 | AD9: =M58 -> 20370.091 | AE9: =M59 -> 35575.858 | AF9: =M60 -> 48956.932 | AG9: =-F9 -> -91445.41 | AH9: =M57+O57 -> 14009.19 | AI9: =M58+O58 -> 30770.091 | AJ9: =M59+O59 -> 45975.858 | AK9: =M60+O60 -> 59356.932 | AL9: 46388 | AM9: 46570 | AN9: 46936 | AO9: 47301 | AP9: 47666
A11: Pacote beneficios (todos os cenarios, por Token I)
A12: Custeio Tokens B (4 anos) | B12: =Premissas!B26 -> 24960 | C12: Abate do payout
A13: Valor a preco de tabela (4 anos) | B13: =Premissas!B28 -> 41600 | C13: 24.960 / 0,60 - marketing + valor economico
A14: Oferta = (VF payout - 24.960) + 41.600 em experiencias
A16: CENARIO: Pessimista | B16: Ocupacao 38% fixa nos 4 anos
A17: Ano | B17: Tendas | C17: Ocupacao | D17: Indice ticket | E17: Diaria | F17: Consumo | G17: Ticket/hosp | H17: Fat 100% | I17: VF Faturamento | J17: VF Royalty 15% | K17: Payout bruto / token | L17: Custeio Token B | M17: Payout liquido (caixa) | N17: Beneficio face | O17: Beneficio tabela | P17: t (mid-period) | Q17: Fator (1+Ke)^t | R17: VP Royalty | S17: VP Payout | T17: Rend. ano caixa | U17: Rend. ano c/ face | V17: Rend. ano c/ tabela
A18: 2027 | B18: =IF(A18=2027,Premissas!$B$13,Premissas!$B$14) -> 6 | C18: =Premissas!B33 -> 0.38 | D18: =(1+Premissas!$B$11)^(A18-2027) -> 1 | E18: =Premissas!$B$6*D18 -> 7333 | F18: =Premissas!$B$7*D18 -> 2000 | G18: =E18*Premissas!$B$8+F18 -> 23999 | H18: =IF(B18=Premissas!$B$13,Premissas!$B$18,Premissas!$B$19)*D18 -> 17279280 | I18: =H18*C18 -> 6566126.4 | J18: =I18*Premissas!$B$12 -> 984918.96 | K18: =J18/Premissas!$B$15 -> 9849.1896 | L18: =Premissas!$B$25 -> 6240 | M18: =K18-L18 -> 3609.1896 | N18: =Premissas!$B$25 -> 6240 | O18: =Premissas!$B$27 -> 10400 | P18: =0.5+(A18-2027) -> 0.5 | Q18: =(1+Ke_WACC!$B$14)^P18 -> 1.0786909 | R18: =J18/Q18 -> 913068.78 | S18: =K18/Q18 -> 9130.6878 | T18: =M18/$B23 -> 0.039740649 | U18: =(M18+N18)/$B23 -> 0.10844905 | V18: =(M18+O18)/$B23 -> 0.15425465
A19: 2028 | B19: =IF(A19=2027,Premissas!$B$13,Premissas!$B$14) -> 20 | C19: =Premissas!C33 -> 0.38 | D19: =(1+Premissas!$B$11)^(A19-2027) -> 1.1 | E19: =Premissas!$B$6*D19 -> 8066.3 | F19: =Premissas!$B$7*D19 -> 2200 | G19: =E19*Premissas!$B$8+F19 -> 26398.9 | H19: =IF(B19=Premissas!$B$13,Premissas!$B$18,Premissas!$B$19)*D19 -> 63357360 | I19: =H19*C19 -> 24075797 | J19: =I19*Premissas!$B$12 -> 3611369.5 | K19: =J19/Premissas!$B$15 -> 36113.695 | L19: =Premissas!$B$25 -> 6240 | M19: =K19-L19 -> 29873.695 | N19: =Premissas!$B$25 -> 6240 | O19: =Premissas!$B$27 -> 10400 | P19: =0.5+(A19-2027) -> 1.5 | Q19: =(1+Ke_WACC!$B$14)^P19 -> 1.2551367 | R19: =J19/Q19 -> 2877272 | S19: =K19/Q19 -> 28772.72 | T19: =M19/$B23 -> 0.32893812 | U19: =(M19+N19)/$B23 -> 0.39764652 | V19: =(M19+O19)/$B23 -> 0.44345212
A20: 2029 | B20: =IF(A20=2027,Premissas!$B$13,Premissas!$B$14) -> 20 | C20: =Premissas!D33 -> 0.38 | D20: =(1+Premissas!$B$11)^(A20-2027) -> 1.21 | E20: =Premissas!$B$6*D20 -> 8872.93 | F20: =Premissas!$B$7*D20 -> 2420 | G20: =E20*Premissas!$B$8+F20 -> 29038.79 | H20: =IF(B20=Premissas!$B$13,Premissas!$B$18,Premissas!$B$19)*D20 -> 69693096 | I20: =H20*C20 -> 26483376 | J20: =I20*Premissas!$B$12 -> 3972506.5 | K20: =J20/Premissas!$B$15 -> 39725.065 | L20: =Premissas!$B$25 -> 6240 | M20: =K20-L20 -> 33485.065 | N20: =Premissas!$B$25 -> 6240 | O20: =Premissas!$B$27 -> 10400 | P20: =0.5+(A20-2027) -> 2.5 | Q20: =(1+Ke_WACC!$B$14)^P20 -> 1.4604444 | R20: =J20/Q20 -> 2720066.9 | S20: =K20/Q20 -> 27200.669 | T20: =M20/$B23 -> 0.36870277 | U20: =(M20+N20)/$B23 -> 0.43741117 | V20: =(M20+O20)/$B23 -> 0.48321677
A21: 2030 | B21: =IF(A21=2027,Premissas!$B$13,Premissas!$B$14) -> 20 | C21: =Premissas!E33 -> 0.38 | D21: =(1+Premissas!$B$11)^(A21-2027) -> 1.331 | E21: =Premissas!$B$6*D21 -> 9760.223 | F21: =Premissas!$B$7*D21 -> 2662 | G21: =E21*Premissas!$B$8+F21 -> 31942.669 | H21: =IF(B21=Premissas!$B$13,Premissas!$B$18,Premissas!$B$19)*D21 -> 76662406 | I21: =H21*C21 -> 29131714 | J21: =I21*Premissas!$B$12 -> 4369757.1 | K21: =J21/Premissas!$B$15 -> 43697.571 | L21: =Premissas!$B$25 -> 6240 | M21: =K21-L21 -> 37457.571 | N21: =Premissas!$B$25 -> 6240 | O21: =Premissas!$B$27 -> 10400 | P21: =0.5+(A21-2027) -> 3.5 | Q21: =(1+Ke_WACC!$B$14)^P21 -> 1.6993351 | R21: =J21/Q21 -> 2571451.1 | S21: =K21/Q21 -> 25714.511 | T21: =M21/$B23 -> 0.41244388 | U21: =(M21+N21)/$B23 -> 0.48115229 | V21: =(M21+O21)/$B23 -> 0.52695789
A22: TOTAL / RESULTADO | I22: =SUM(I18:I21) -> 86257014 | J22: =SUM(J18:J21) -> 12938552 | K22: =SUM(K18:K21) -> 129385.52 | L22: =SUM(L18:L21) -> 24960 | M22: =SUM(M18:M21) -> 104425.52 | N22: =SUM(N18:N21) -> 24960 | O22: =SUM(O18:O21) -> 41600 | R22: =SUM(R18:R21) -> 9081858.8 | S22: =SUM(S18:S21) -> 90818.588 | T22: =AVERAGE(T18:T21) -> 0.28745635 | U22: =AVERAGE(U18:U21) -> 0.35616476 | V22: =AVERAGE(V18:V21) -> 0.40197036
A23: Preco do Token I (VP payout) | B23: =S22 -> 90818.588
A24: VP integral (100 tokens) | B24: =B23*Premissas!$B$15 -> 9081858.8
A25: Captacao IBITI (67 tokens externos) | B25: =B23*Premissas!$B$16 -> 6084845.4 | C25: 67 tokens externos
A26: Multiplo VF bruto / preco | B26: =K22/B23 -> 1.424659
A27: Pacote ao holder: caixa liquido VF | B27: =M22 -> 104425.52 | C27: + beneficios tabela | D27: =Premissas!$B$28 -> 41600 | E27: = total economico | F27: =B27+D27 -> 146025.52
A29: CENARIO: Base | B29: Ocupacao 38% / 40% / 45% / 50%
A30: Ano | B30: Tendas | C30: Ocupacao | D30: Indice ticket | E30: Diaria | F30: Consumo | G30: Ticket/hosp | H30: Fat 100% | I30: VF Faturamento | J30: VF Royalty 15% | K30: Payout bruto / token | L30: Custeio Token B | M30: Payout liquido (caixa) | N30: Beneficio face | O30: Beneficio tabela | P30: t (mid-period) | Q30: Fator (1+Ke)^t | R30: VP Royalty | S30: VP Payout | T30: Rend. ano caixa | U30: Rend. ano c/ face | V30: Rend. ano c/ tabela
A31: 2027 | B31: =IF(A31=2027,Premissas!$B$13,Premissas!$B$14) -> 6 | C31: =Premissas!B34 -> 0.38 | D31: =(1+Premissas!$B$11)^(A31-2027) -> 1 | E31: =Premissas!$B$6*D31 -> 7333 | F31: =Premissas!$B$7*D31 -> 2000 | G31: =E31*Premissas!$B$8+F31 -> 23999 | H31: =IF(B31=Premissas!$B$13,Premissas!$B$18,Premissas!$B$19)*D31 -> 17279280 | I31: =H31*C31 -> 6566126.4 | J31: =I31*Premissas!$B$12 -> 984918.96 | K31: =J31/Premissas!$B$15 -> 9849.1896 | L31: =Premissas!$B$25 -> 6240 | M31: =K31-L31 -> 3609.1896 | N31: =Premissas!$B$25 -> 6240 | O31: =Premissas!$B$27 -> 10400 | P31: =0.5+(A31-2027) -> 0.5 | Q31: =(1+Ke_WACC!$B$14)^P31 -> 1.0786909 | R31: =J31/Q31 -> 913068.78 | S31: =K31/Q31 -> 9130.6878 | T31: =M31/$B36 -> 0.034222018 | U31: =(M31+N31)/$B36 -> 0.093389147 | V31: =(M31+O31)/$B36 -> 0.1328339
A32: 2028 | B32: =IF(A32=2027,Premissas!$B$13,Premissas!$B$14) -> 20 | C32: =Premissas!C34 -> 0.4 | D32: =(1+Premissas!$B$11)^(A32-2027) -> 1.1 | E32: =Premissas!$B$6*D32 -> 8066.3 | F32: =Premissas!$B$7*D32 -> 2200 | G32: =E32*Premissas!$B$8+F32 -> 26398.9 | H32: =IF(B32=Premissas!$B$13,Premissas!$B$18,Premissas!$B$19)*D32 -> 63357360 | I32: =H32*C32 -> 25342944 | J32: =I32*Premissas!$B$12 -> 3801441.6 | K32: =J32/Premissas!$B$15 -> 38014.416 | L32: =Premissas!$B$25 -> 6240 | M32: =K32-L32 -> 31774.416 | N32: =Premissas!$B$25 -> 6240 | O32: =Premissas!$B$27 -> 10400 | P32: =0.5+(A32-2027) -> 1.5 | Q32: =(1+Ke_WACC!$B$14)^P32 -> 1.2551367 | R32: =J32/Q32 -> 3028707.3 | S32: =K32/Q32 -> 30287.073 | T32: =M32/$B36 -> 0.30128221 | U32: =(M32+N32)/$B36 -> 0.36044934 | V32: =(M32+O32)/$B36 -> 0.39989409
A33: 2029 | B33: =IF(A33=2027,Premissas!$B$13,Premissas!$B$14) -> 20 | C33: =Premissas!D34 -> 0.45 | D33: =(1+Premissas!$B$11)^(A33-2027) -> 1.21 | E33: =Premissas!$B$6*D33 -> 8872.93 | F33: =Premissas!$B$7*D33 -> 2420 | G33: =E33*Premissas!$B$8+F33 -> 29038.79 | H33: =IF(B33=Premissas!$B$13,Premissas!$B$18,Premissas!$B$19)*D33 -> 69693096 | I33: =H33*C33 -> 31361893 | J33: =I33*Premissas!$B$12 -> 4704284 | K33: =J33/Premissas!$B$15 -> 47042.84 | L33: =Premissas!$B$25 -> 6240 | M33: =K33-L33 -> 40802.84 | N33: =Premissas!$B$25 -> 6240 | O33: =Premissas!$B$27 -> 10400 | P33: =0.5+(A33-2027) -> 2.5 | Q33: =(1+Ke_WACC!$B$14)^P33 -> 1.4604444 | R33: =J33/Q33 -> 3221131.9 | S33: =K33/Q33 -> 32211.319 | T33: =M33/$B36 -> 0.38688893 | U33: =(M33+N33)/$B36 -> 0.44605606 | V33: =(M33+O33)/$B36 -> 0.48550081
A34: 2030 | B34: =IF(A34=2027,Premissas!$B$13,Premissas!$B$14) -> 20 | C34: =Premissas!E34 -> 0.5 | D34: =(1+Premissas!$B$11)^(A34-2027) -> 1.331 | E34: =Premissas!$B$6*D34 -> 9760.223 | F34: =Premissas!$B$7*D34 -> 2662 | G34: =E34*Premissas!$B$8+F34 -> 31942.669 | H34: =IF(B34=Premissas!$B$13,Premissas!$B$18,Premissas!$B$19)*D34 -> 76662406 | I34: =H34*C34 -> 38331203 | J34: =I34*Premissas!$B$12 -> 5749680.4 | K34: =J34/Premissas!$B$15 -> 57496.804 | L34: =Premissas!$B$25 -> 6240 | M34: =K34-L34 -> 51256.804 | N34: =Premissas!$B$25 -> 6240 | O34: =Premissas!$B$27 -> 10400 | P34: =0.5+(A34-2027) -> 3.5 | Q34: =(1+Ke_WACC!$B$14)^P34 -> 1.6993351 | R34: =J34/Q34 -> 3383488.3 | S34: =K34/Q34 -> 33834.883 | T34: =M34/$B36 -> 0.4860125 | U34: =(M34+N34)/$B36 -> 0.54517963 | V34: =(M34+O34)/$B36 -> 0.58462438
A35: TOTAL / RESULTADO | I35: =SUM(I31:I34) -> 1.0160217e+08 | J35: =SUM(J31:J34) -> 15240325 | K35: =SUM(K31:K34) -> 152403.25 | L35: =SUM(L31:L34) -> 24960 | M35: =SUM(M31:M34) -> 127443.25 | N35: =SUM(N31:N34) -> 24960 | O35: =SUM(O31:O34) -> 41600 | R35: =SUM(R31:R34) -> 10546396 | S35: =SUM(S31:S34) -> 105463.96 | T35: =AVERAGE(T31:T34) -> 0.30210141 | U35: =AVERAGE(U31:U34) -> 0.36126854 | V35: =AVERAGE(V31:V34) -> 0.4007133
A36: Preco do Token I (VP payout) | B36: =S35 -> 105463.96
A37: VP integral (100 tokens) | B37: =B36*Premissas!$B$15 -> 10546396
A38: Captacao IBITI (67 tokens externos) | B38: =B36*Premissas!$B$16 -> 7066085.5 | C38: 67 tokens externos
A39: Multiplo VF bruto / preco | B39: =K35/B36 -> 1.4450742
A40: Pacote ao holder: caixa liquido VF | B40: =M35 -> 127443.25 | C40: + beneficios tabela | D40: =Premissas!$B$28 -> 41600 | E40: = total economico | F40: =B40+D40 -> 169043.25
A42: CENARIO: Otimista | B42: Ocupacao 38% / 50% / 50% / 50%
A43: Ano | B43: Tendas | C43: Ocupacao | D43: Indice ticket | E43: Diaria | F43: Consumo | G43: Ticket/hosp | H43: Fat 100% | I43: VF Faturamento | J43: VF Royalty 15% | K43: Payout bruto / token | L43: Custeio Token B | M43: Payout liquido (caixa) | N43: Beneficio face | O43: Beneficio tabela | P43: t (mid-period) | Q43: Fator (1+Ke)^t | R43: VP Royalty | S43: VP Payout | T43: Rend. ano caixa | U43: Rend. ano c/ face | V43: Rend. ano c/ tabela
A44: 2027 | B44: =IF(A44=2027,Premissas!$B$13,Premissas!$B$14) -> 6 | C44: =Premissas!B35 -> 0.38 | D44: =(1+Premissas!$B$11)^(A44-2027) -> 1 | E44: =Premissas!$B$6*D44 -> 7333 | F44: =Premissas!$B$7*D44 -> 2000 | G44: =E44*Premissas!$B$8+F44 -> 23999 | H44: =IF(B44=Premissas!$B$13,Premissas!$B$18,Premissas!$B$19)*D44 -> 17279280 | I44: =H44*C44 -> 6566126.4 | J44: =I44*Premissas!$B$12 -> 984918.96 | K44: =J44/Premissas!$B$15 -> 9849.1896 | L44: =Premissas!$B$25 -> 6240 | M44: =K44-L44 -> 3609.1896 | N44: =Premissas!$B$25 -> 6240 | O44: =Premissas!$B$27 -> 10400 | P44: =0.5+(A44-2027) -> 0.5 | Q44: =(1+Ke_WACC!$B$14)^P44 -> 1.0786909 | R44: =J44/Q44 -> 913068.78 | S44: =K44/Q44 -> 9130.6878 | T44: =M44/$B49 -> 0.030949679 | U44: =(M44+N44)/$B49 -> 0.084459197 | V44: =(M44+O44)/$B49 -> 0.12013221
A45: 2028 | B45: =IF(A45=2027,Premissas!$B$13,Premissas!$B$14) -> 20 | C45: =Premissas!C35 -> 0.5 | D45: =(1+Premissas!$B$11)^(A45-2027) -> 1.1 | E45: =Premissas!$B$6*D45 -> 8066.3 | F45: =Premissas!$B$7*D45 -> 2200 | G45: =E45*Premissas!$B$8+F45 -> 26398.9 | H45: =IF(B45=Premissas!$B$13,Premissas!$B$18,Premissas!$B$19)*D45 -> 63357360 | I45: =H45*C45 -> 31678680 | J45: =I45*Premissas!$B$12 -> 4751802 | K45: =J45/Premissas!$B$15 -> 47518.02 | L45: =Premissas!$B$25 -> 6240 | M45: =K45-L45 -> 41278.02 | N45: =Premissas!$B$25 -> 6240 | O45: =Premissas!$B$27 -> 10400 | P45: =0.5+(A45-2027) -> 1.5 | Q45: =(1+Ke_WACC!$B$14)^P45 -> 1.2551367 | R45: =J45/Q45 -> 3785884.2 | S45: =K45/Q45 -> 37858.842 | T45: =M45/$B49 -> 0.35396906 | U45: =(M45+N45)/$B49 -> 0.40747858 | V45: =(M45+O45)/$B49 -> 0.4431516
A46: 2029 | B46: =IF(A46=2027,Premissas!$B$13,Premissas!$B$14) -> 20 | C46: =Premissas!D35 -> 0.5 | D46: =(1+Premissas!$B$11)^(A46-2027) -> 1.21 | E46: =Premissas!$B$6*D46 -> 8872.93 | F46: =Premissas!$B$7*D46 -> 2420 | G46: =E46*Premissas!$B$8+F46 -> 29038.79 | H46: =IF(B46=Premissas!$B$13,Premissas!$B$18,Premissas!$B$19)*D46 -> 69693096 | I46: =H46*C46 -> 34846548 | J46: =I46*Premissas!$B$12 -> 5226982.2 | K46: =J46/Premissas!$B$15 -> 52269.822 | L46: =Premissas!$B$25 -> 6240 | M46: =K46-L46 -> 46029.822 | N46: =Premissas!$B$25 -> 6240 | O46: =Premissas!$B$27 -> 10400 | P46: =0.5+(A46-2027) -> 2.5 | Q46: =(1+Ke_WACC!$B$14)^P46 -> 1.4604444 | R46: =J46/Q46 -> 3579035.5 | S46: =K46/Q46 -> 35790.355 | T46: =M46/$B49 -> 0.39471692 | U46: =(M46+N46)/$B49 -> 0.44822644 | V46: =(M46+O46)/$B49 -> 0.48389945
A47: 2030 | B47: =IF(A47=2027,Premissas!$B$13,Premissas!$B$14) -> 20 | C47: =Premissas!E35 -> 0.5 | D47: =(1+Premissas!$B$11)^(A47-2027) -> 1.331 | E47: =Premissas!$B$6*D47 -> 9760.223 | F47: =Premissas!$B$7*D47 -> 2662 | G47: =E47*Premissas!$B$8+F47 -> 31942.669 | H47: =IF(B47=Premissas!$B$13,Premissas!$B$18,Premissas!$B$19)*D47 -> 76662406 | I47: =H47*C47 -> 38331203 | J47: =I47*Premissas!$B$12 -> 5749680.4 | K47: =J47/Premissas!$B$15 -> 57496.804 | L47: =Premissas!$B$25 -> 6240 | M47: =K47-L47 -> 51256.804 | N47: =Premissas!$B$25 -> 6240 | O47: =Premissas!$B$27 -> 10400 | P47: =0.5+(A47-2027) -> 3.5 | Q47: =(1+Ke_WACC!$B$14)^P47 -> 1.6993351 | R47: =J47/Q47 -> 3383488.3 | S47: =K47/Q47 -> 33834.883 | T47: =M47/$B49 -> 0.43953957 | U47: =(M47+N47)/$B49 -> 0.49304909 | V47: =(M47+O47)/$B49 -> 0.5287221
A48: TOTAL / RESULTADO | I48: =SUM(I44:I47) -> 1.1142256e+08 | J48: =SUM(J44:J47) -> 16713384 | K48: =SUM(K44:K47) -> 167133.84 | L48: =SUM(L44:L47) -> 24960 | M48: =SUM(M44:M47) -> 142173.84 | N48: =SUM(N44:N47) -> 24960 | O48: =SUM(O44:O47) -> 41600 | R48: =SUM(R44:R47) -> 11661477 | S48: =SUM(S44:S47) -> 116614.77 | T48: =AVERAGE(T44:T47) -> 0.30479381 | U48: =AVERAGE(U44:U47) -> 0.35830333 | V48: =AVERAGE(V44:V47) -> 0.39397634
A49: Preco do Token I (VP payout) | B49: =S48 -> 116614.77
A50: VP integral (100 tokens) | B50: =B49*Premissas!$B$15 -> 11661477
A51: Captacao IBITI (67 tokens externos) | B51: =B49*Premissas!$B$16 -> 7813189.4 | C51: 67 tokens externos
A52: Multiplo VF bruto / preco | B52: =K48/B49 -> 1.4332133
A53: Pacote ao holder: caixa liquido VF | B53: =M48 -> 142173.84 | C53: + beneficios tabela | D53: =Premissas!$B$28 -> 41600 | E53: = total economico | F53: =B53+D53 -> 183773.84
A55: CENARIO: Expansao (queda ano 2) | B55: 38% em 2027; cai para 28% em 2028 (diluicao pela expansao 6 para 20); recupera 40% e 48%
A56: Ano | B56: Tendas | C56: Ocupacao | D56: Indice ticket | E56: Diaria | F56: Consumo | G56: Ticket/hosp | H56: Fat 100% | I56: VF Faturamento | J56: VF Royalty 15% | K56: Payout bruto / token | L56: Custeio Token B | M56: Payout liquido (caixa) | N56: Beneficio face | O56: Beneficio tabela | P56: t (mid-period) | Q56: Fator (1+Ke)^t | R56: VP Royalty | S56: VP Payout | T56: Rend. ano caixa | U56: Rend. ano c/ face | V56: Rend. ano c/ tabela
A57: 2027 | B57: =IF(A57=2027,Premissas!$B$13,Premissas!$B$14) -> 6 | C57: =Premissas!B36 -> 0.38 | D57: =(1+Premissas!$B$11)^(A57-2027) -> 1 | E57: =Premissas!$B$6*D57 -> 7333 | F57: =Premissas!$B$7*D57 -> 2000 | G57: =E57*Premissas!$B$8+F57 -> 23999 | H57: =IF(B57=Premissas!$B$13,Premissas!$B$18,Premissas!$B$19)*D57 -> 17279280 | I57: =H57*C57 -> 6566126.4 | J57: =I57*Premissas!$B$12 -> 984918.96 | K57: =J57/Premissas!$B$15 -> 9849.1896 | L57: =Premissas!$B$25 -> 6240 | M57: =K57-L57 -> 3609.1896 | N57: =Premissas!$B$25 -> 6240 | O57: =Premissas!$B$27 -> 10400 | P57: =0.5+(A57-2027) -> 0.5 | Q57: =(1+Ke_WACC!$B$14)^P57 -> 1.0786909 | R57: =J57/Q57 -> 913068.78 | S57: =K57/Q57 -> 9130.6878 | T57: =M57/$B62 -> 0.039468242 | U57: =(M57+N57)/$B62 -> 0.10770567 | V57: =(M57+O57)/$B62 -> 0.1531973
A58: 2028 | B58: =IF(A58=2027,Premissas!$B$13,Premissas!$B$14) -> 20 | C58: =Premissas!C36 -> 0.28 | D58: =(1+Premissas!$B$11)^(A58-2027) -> 1.1 | E58: =Premissas!$B$6*D58 -> 8066.3 | F58: =Premissas!$B$7*D58 -> 2200 | G58: =E58*Premissas!$B$8+F58 -> 26398.9 | H58: =IF(B58=Premissas!$B$13,Premissas!$B$18,Premissas!$B$19)*D58 -> 63357360 | I58: =H58*C58 -> 17740061 | J58: =I58*Premissas!$B$12 -> 2661009.1 | K58: =J58/Premissas!$B$15 -> 26610.091 | L58: =Premissas!$B$25 -> 6240 | M58: =K58-L58 -> 20370.091 | N58: =Premissas!$B$25 -> 6240 | O58: =Premissas!$B$27 -> 10400 | P58: =0.5+(A58-2027) -> 1.5 | Q58: =(1+Ke_WACC!$B$14)^P58 -> 1.2551367 | R58: =J58/Q58 -> 2120095.1 | S58: =K58/Q58 -> 21200.951 | T58: =M58/$B62 -> 0.22275685 | U58: =(M58+N58)/$B62 -> 0.29099428 | V58: =(M58+O58)/$B62 -> 0.3364859
A59: 2029 | B59: =IF(A59=2027,Premissas!$B$13,Premissas!$B$14) -> 20 | C59: =Premissas!D36 -> 0.4 | D59: =(1+Premissas!$B$11)^(A59-2027) -> 1.21 | E59: =Premissas!$B$6*D59 -> 8872.93 | F59: =Premissas!$B$7*D59 -> 2420 | G59: =E59*Premissas!$B$8+F59 -> 29038.79 | H59: =IF(B59=Premissas!$B$13,Premissas!$B$18,Premissas!$B$19)*D59 -> 69693096 | I59: =H59*C59 -> 27877238 | J59: =I59*Premissas!$B$12 -> 4181585.8 | K59: =J59/Premissas!$B$15 -> 41815.858 | L59: =Premissas!$B$25 -> 6240 | M59: =K59-L59 -> 35575.858 | N59: =Premissas!$B$25 -> 6240 | O59: =Premissas!$B$27 -> 10400 | P59: =0.5+(A59-2027) -> 2.5 | Q59: =(1+Ke_WACC!$B$14)^P59 -> 1.4604444 | R59: =J59/Q59 -> 2863228.4 | S59: =K59/Q59 -> 28632.284 | T59: =M59/$B62 -> 0.38903929 | U59: =(M59+N59)/$B62 -> 0.45727672 | V59: =(M59+O59)/$B62 -> 0.50276834
A60: 2030 | B60: =IF(A60=2027,Premissas!$B$13,Premissas!$B$14) -> 20 | C60: =Premissas!E36 -> 0.48 | D60: =(1+Premissas!$B$11)^(A60-2027) -> 1.331 | E60: =Premissas!$B$6*D60 -> 9760.223 | F60: =Premissas!$B$7*D60 -> 2662 | G60: =E60*Premissas!$B$8+F60 -> 31942.669 | H60: =IF(B60=Premissas!$B$13,Premissas!$B$18,Premissas!$B$19)*D60 -> 76662406 | I60: =H60*C60 -> 36797955 | J60: =I60*Premissas!$B$12 -> 5519693.2 | K60: =J60/Premissas!$B$15 -> 55196.932 | L60: =Premissas!$B$25 -> 6240 | M60: =K60-L60 -> 48956.932 | N60: =Premissas!$B$25 -> 6240 | O60: =Premissas!$B$27 -> 10400 | P60: =0.5+(A60-2027) -> 3.5 | Q60: =(1+Ke_WACC!$B$14)^P60 -> 1.6993351 | R60: =J60/Q60 -> 3248148.8 | S60: =K60/Q60 -> 32481.488 | T60: =M60/$B62 -> 0.53536784 | U60: =(M60+N60)/$B62 -> 0.60360527 | V60: =(M60+O60)/$B62 -> 0.6490969
A61: TOTAL / RESULTADO | I61: =SUM(I57:I60) -> 88981380 | J61: =SUM(J57:J60) -> 13347207 | K61: =SUM(K57:K60) -> 133472.07 | L61: =SUM(L57:L60) -> 24960 | M61: =SUM(M57:M60) -> 108512.07 | N61: =SUM(N57:N60) -> 24960 | O61: =SUM(O57:O60) -> 41600 | R61: =SUM(R57:R60) -> 9144541 | S61: =SUM(S57:S60) -> 91445.41 | T61: =AVERAGE(T57:T60) -> 0.29665806 | U61: =AVERAGE(U57:U60) -> 0.36489549 | V61: =AVERAGE(V57:V60) -> 0.41038711
A62: Preco do Token I (VP payout) | B62: =S61 -> 91445.41
A63: VP integral (100 tokens) | B63: =B62*Premissas!$B$15 -> 9144541
A64: Captacao IBITI (67 tokens externos) | B64: =B62*Premissas!$B$16 -> 6126842.5 | C64: 67 tokens externos
A65: Multiplo VF bruto / preco | B65: =K61/B62 -> 1.459582
A66: Pacote ao holder: caixa liquido VF | B66: =M61 -> 108512.07 | C66: + beneficios tabela | D66: =Premissas!$B$28 -> 41600 | E66: = total economico | F66: =B66+D66 -> 150112.07

Sheet Ke_WACC
A1: K_e (custo de capital proprio) - aba tecnica
A2: No projeto usamos K_e (CAPM). O termo WACC aparece no HTML legado; a taxa de desconto do token e K_e.
A4: Insumos
A5: Parametro | B5: Valor | C5: Fonte / nota
A6: NTN-B (taxa real) | B6: 0.0802 | C6: Titulo IPCA+
A7: Inflacao esperada | B7: 0.035 | C7: Premissa Fisher
A8: Beta desalavancado (b_u) | B8: 0.61 | C8: Damodaran / setor
A9: Premio de risco de mercado (PRM) | B9: 0.0747 | C9: Damodaran Brasil
A10: Data-base / referência temporal | B10: set/2026 | C10: Memorando com data-base set/2026. Por orientação do professor, o DCF anual usa convenção mid-period: 2027=t0,5; 2028=t1,5; 2029=t2,5; 2030=t3,5.
A11: Calculo
A12: r_f nominal (Fisher) = (1+NTN-B)x(1+inf)-1 | B12: =(1+B6)*(1+B7)-1 -> 0.118007 | C12: Taxa livre de risco nominal
A13: Premio = b_u x PRM | B13: =B8*B9 -> 0.045567
A14: K_e = r_f + b_u x PRM | B14: =B12+B13 -> 0.163574 | C14: Taxa de desconto do DCF do token
A15: K_e arredondado (referencia HTML) | B15: =ROUND(B14,4) -> 0.1636 | C15: ~ 16,36% a.a.
A17: Convenção de desconto - MID-PERIOD
A18: t = 0,5 + (ano - 2027) | C18: Fluxos anuais são aproximados pelo ponto médio de cada período, refletindo geração/recebimento ao longo do ano.
A19: Fator 2027 | B19: =(1+$B$14)^0.5 -> 1.0786909 | C19: (1+Ke)^0,5
A20: Fator 2028 | B20: =(1+$B$14)^1.5 -> 1.2551367 | C20: (1+Ke)^1,5
A21: Fator 2029 | B21: =(1+$B$14)^2.5 -> 1.4604444 | C21: (1+Ke)^2,5
A22: Fator 2030 | B22: =(1+$B$14)^3.5 -> 1.6993351 | C22: (1+Ke)^3,5
A24: Mid-period: como os royalties são gerados ao longo de cada exercício, o modelo aproxima o recebimento médio no meio do período. Convenção acadêmica validada pelo professor: t = 0,5; 1,5; 2,5; 3,5.
